single_bot/__init__.py
single_bot/auth_manager.py
single_bot/bot.py
single_bot/bot_factory.py
single_bot/config.py
single_bot/data_types.py
single_bot/database.py
single_bot/logger.py
single_bot/messengers.py
single_bot/user_state.py
single_bot-0.2.3.dist-info/METADATA
single_bot-0.2.3.dist-info/WHEEL
single_bot-0.2.3.dist-info/top_level.txt
single_bot-0.2.3.dist-info/RECORD
